SNBT/__init__.py
SNBT-0.0.2.dist-info/LICENSE
SNBT-0.0.2.dist-info/METADATA
SNBT-0.0.2.dist-info/WHEEL
SNBT-0.0.2.dist-info/top_level.txt
SNBT-0.0.2.dist-info/RECORD
