Metadata-Version: 2.1
Name: SNBT
Version: 0.0.2
Summary: A library that generates SNBT strings for Minecraft
Author-email: HellishBro <hellishbroamongus@gmail.com>
Classifier: Programming Language :: Python :: 3
Classifier: License :: OSI Approved :: MIT License
Classifier: Operating System :: OS Independent
Requires-Python: >=3.6
License-File: LICENSE
